bolivia_cc/__init__.py
bolivia_cc/__main__.py
bolivia_cc/cli.py
bolivia_cc/controlcode.py
bolivia_cc/utils.py
bolivia_cc-0.1.3a0.dist-info/LICENSE
bolivia_cc-0.1.3a0.dist-info/WHEEL
bolivia_cc-0.1.3a0.dist-info/entry_points.txt
bolivia_cc-0.1.3a0.dist-info/METADATA
bolivia_cc-0.1.3a0.dist-info/RECORD
