Metadata-Version: 2.1
Name: bolivia-cc
Version: 0.1.3a0
Summary: El código de control es un dato alfanumérico generado por un sistema de facturación y sirve para determinar la validez o no de una factura en Bolivia.
Home-page: https://github.com/tugerente-com/bolivia-cc
License: Apache-2.0
Keywords: bolivia,codigo control,impuestos
Requires-Python: >=3.8,<4.0
Classifier: Development Status :: 4 - Beta
Classifier: Environment :: Console
Classifier: Intended Audience :: Developers
Classifier: License :: OSI Approved :: Apache Software License
Classifier: Natural Language :: Spanish
Classifier: Programming Language :: Python
Classifier: Programming Language :: Python :: 3
Classifier: Programming Language :: Python :: 3.8
Classifier: Programming Language :: Python :: 3.9
Classifier: Programming Language :: Python :: 3.10
Classifier: Programming Language :: Python :: 3.11
Classifier: Programming Language :: Python :: 3.8
Project-URL: Changelog, https://github.com/tugerente-com/bolivia-cc
Project-URL: Documentation, https://github.com/tugerente-com/bolivia-cc
Project-URL: Repository, https://github.com/tugerente-com/bolivia-cc
Project-URL: Support, https://github.com/tugerente-com/bolivia-cc
